freekassa_ru/__init__.py
freekassa_ru/errors.py
freekassa_ru/freekassa.py
freekassa_ru/notification.py
freekassa_ru-0.0.7.dist-info/LICENSE
freekassa_ru-0.0.7.dist-info/METADATA
freekassa_ru-0.0.7.dist-info/WHEEL
freekassa_ru-0.0.7.dist-info/top_level.txt
freekassa_ru-0.0.7.dist-info/RECORD
