Metadata-Version: 2.1
Name: freekassa_ru
Version: 0.0.7
Summary: Library for using service https://docs.freekassa.ru/
Home-page: https://github.com/klishinoleg/freekassa
Author: Klishin Oleg
Author-email: klishinoleg@gmail.com
Project-URL: Bug Tracker, https://github.com/klishinoleg/freekassa/issues
Classifier: Programming Language :: Python :: 3.7
Classifier: License :: OSI Approved :: MIT License
Classifier: Operating System :: OS Independent
Requires-Python: >=3.7
License-File: LICENSE
